ssub/__init__.py
ssub/schema.json
ssub/subscriber.py
ssub/scripts/__init__.py
ssub/scripts/create_notification_configuration.py
ssub/scripts/launch_ssub.py
ssub/scripts/send_test_email.py
ssub-0.2.1.data/scripts/create_notification_configuration.py
ssub-0.2.1.data/scripts/launch_ssub.py
ssub-0.2.1.data/scripts/send_test_email.py
ssub-0.2.1.dist-info/METADATA
ssub-0.2.1.dist-info/WHEEL
ssub-0.2.1.dist-info/entry_points.txt
ssub-0.2.1.dist-info/top_level.txt
ssub-0.2.1.dist-info/RECORD
