Metadata-Version: 2.1
Name: ssub
Version: 0.2.1
Summary: Polls a GCP Pub/Sub topic for new SampleSheet notification messages in order to initiate bcl2fastq.
Home-page: https://pypi.org/project/ssub/
Author: Nathaniel Watson
Author-email: nathan.watson86@gmail.com
License: UNKNOWN
Project-URL: Read the Docs, https://ssub.readthedocs.io/en/latest
Keywords: bcl2fastq sequencing samplesheet monitor
Platform: UNKNOWN
Classifier: Programming Language :: Python :: 3
Classifier: License :: OSI Approved :: MIT License
Classifier: Operating System :: OS Independent
Requires-Dist: sruns-monitor
